dash_websocket_component/DashWebsocketComponent.py
dash_websocket_component/__init__.py
dash_websocket_component/_imports_.py
dash_websocket_component/async-DashWebsocketComponent.js
dash_websocket_component/async-DashWebsocketComponent.js.map
dash_websocket_component/dash_websocket_component.min.js
dash_websocket_component/dash_websocket_component.min.js.map
dash_websocket_component/metadata.json
dash_websocket_component/package-info.json
dash_websocket_component-1.0.0.dist-info/LICENSE
dash_websocket_component-1.0.0.dist-info/METADATA
dash_websocket_component-1.0.0.dist-info/WHEEL
dash_websocket_component-1.0.0.dist-info/top_level.txt
dash_websocket_component-1.0.0.dist-info/RECORD
