Metadata-Version: 2.1
Name: dash-websocket-component
Version: 1.0.0
Summary: Project Description
Author: Dominik Tkacik <tkacik38@gmail.com>
License: MIT
Classifier: Framework :: Dash
License-File: LICENSE
